whisper_spln/__init__.py
whisper_spln/listener.py
whisper_spln/lockedQueue.py
whisper_spln/main.py
whisper_spln/parserTasks.py
whisper_spln/startThreads.py
whisper_spln/worker.py
whisper_spln/conf/error.log
whisper_spln/conf/exec_time
whisper_spln/conf/output.log
whisper_spln-0.5.dist-info/entry_points.txt
whisper_spln-0.5.dist-info/LICENSE
whisper_spln-0.5.dist-info/WHEEL
whisper_spln-0.5.dist-info/METADATA
whisper_spln-0.5.dist-info/RECORD
