Metadata-Version: 2.1
Name: whisper_spln
Version: 0.5
Summary: Whisper SPLN is a remote service that allows a user to transcrive audio files to text using whisper from openai. 
Author-email: João <joaoandre210@gmail.com>, Jorge <jorge.lima.ne@gmail.com>, Cristiano <pg5034@alunos.uminho.pt>
Classifier: License :: OSI Approved :: MIT License
Requires-Dist: whisper
Requires-Dist: googletrans==4.0.0-rc1
